LICENSE
README.md
setup.cfg
setup.py
pangocffi/VERSION
pangocffi/__init__.py
pangocffi/attr_list.py
pangocffi/attribute.py
pangocffi/c_definitions_glib.txt
pangocffi/c_definitions_pango.txt
pangocffi/color.py
pangocffi/context.py
pangocffi/convert.py
pangocffi/enums.py
pangocffi/ffi_build.py
pangocffi/ffi_instance_builder.py
pangocffi/font.py
pangocffi/font_description.py
pangocffi/font_metrics.py
pangocffi/glyph_item.py
pangocffi/glyph_item_iter.py
pangocffi/item.py
pangocffi/language.py
pangocffi/layout.py
pangocffi/layout_iter.py
pangocffi/layout_run.py
pangocffi/pango_object.py
pangocffi/rectangle.py
pangocffi/tab_array.py
pangocffi/version.py
pangocffi.egg-info/PKG-INFO
pangocffi.egg-info/SOURCES.txt
pangocffi.egg-info/dependency_links.txt
pangocffi.egg-info/requires.txt
pangocffi.egg-info/top_level.txt
tests/acceptance/__init__.py
tests/acceptance/test_attributes.py
tests/acceptance/test_tab_array.py