Metadata-Version: 2.1
Name: pangocffi
Version: 0.13.0
Summary: CFFI-based pango bindings for Python
Home-page: https://github.com/leifgehrmann/pangocffi
Author: Leif Gehrmann
License: LGPL-2.1
Project-URL: Code, https://github.com/leifgehrmann/pangocffi
Project-URL: Issue tracker, https://github.com/leifgehrmann/pangocffi/issues
Keywords: pango,cffi,binding
Classifier: Development Status :: 1 - Planning
Classifier: Intended Audience :: Developers
Classifier: Natural Language :: English
Classifier: Programming Language :: Python :: 3 :: Only
Classifier: Programming Language :: Python :: 3.8
Classifier: Programming Language :: Python :: 3.9
Classifier: Programming Language :: Python :: 3.10
Classifier: Programming Language :: Python :: 3.11
Classifier: Programming Language :: Python :: 3.12
Classifier: Topic :: Text Processing :: Fonts
Requires-Python: >=3.8
License-File: LICENSE
Requires-Dist: cffi>=1.1.0
